qfit/.pylintrc
qfit/__init__.py
qfit/settings.py
qfit/version.py
qfit/controllers/__init__.py
qfit/controllers/calibration_ctrl.py
qfit/controllers/extracting_ctrl.py
qfit/controllers/fit_ctrl.py
qfit/controllers/help_tooltip.py
qfit/controllers/io_ctrl.py
qfit/controllers/meas_data_ctrl.py
qfit/controllers/plotting_ctrl.py
qfit/controllers/prefit_ctrl.py
qfit/controllers/settings.py
qfit/controllers/status.py
qfit/core/__init__.py
qfit/core/mainwindow.py
qfit/core/qfit.py
qfit/models/__init__.py
qfit/models/calibration.py
qfit/models/data_structures.py
qfit/models/extracted_data.py
qfit/models/fit.py
qfit/models/measurement_data.py
qfit/models/numerical_model.py
qfit/models/parameter_set.py
qfit/models/parameter_settings.py
qfit/models/prefit.py
qfit/models/registry.py
qfit/models/status.py
qfit/ui_designer/__init__.py
qfit/ui_designer/resources_rc.py
qfit/ui_designer/settings.py
qfit/ui_designer/settings_fit.py
qfit/ui_designer/settings_numerical_spectrum.py
qfit/ui_designer/settings_visual.py
qfit/ui_designer/ui_menu.py
qfit/ui_designer/ui_window.py
qfit/utils/__init__.py
qfit/utils/export.py
qfit/utils/helpers.py
qfit/utils/load_reg_dict.py
qfit/utils/run_by_scripts.py
qfit/utils/wrapped_optimizer.py
qfit/views/__init__.py
qfit/views/calibration_view.py
qfit/views/fit_view.py
qfit/views/importer_view.py
qfit/views/labeling_view.py
qfit/views/meas_data_view.py
qfit/views/paging_view.py
qfit/views/prefit_view.py
qfit/views/status_bar.py
qfit/widgets/__init__.py
qfit/widgets/custom_status_bar.py
qfit/widgets/custom_table.py
qfit/widgets/data_extracting.py
qfit/widgets/foldable_widget.py
qfit/widgets/gif_tooltip.py
qfit/widgets/grouped_sliders.py
qfit/widgets/menu.py
qfit/widgets/mpl_canvas.py
qfit/widgets/settings.py
qfit/widgets/validated_line_edits.py
qfit-3.0.2.dist-info/licenses/LICENSE
qfit-3.0.2.dist-info/METADATA
qfit-3.0.2.dist-info/WHEEL
qfit-3.0.2.dist-info/top_level.txt
qfit-3.0.2.dist-info/RECORD
