Metadata-Version: 2.4
Name: qfit
Version: 3.0.2
Summary: QFit: Interactive Parameter Fitting for Superconducting Circuits
Author-email: Tianpu Zhao <tianpuzhao2022@u.northwestern.edu>, Danyang Chen <danyangchen2026@u.northwestern.edu>, Jens Koch <jens-koch@northwestern.edu>
License: BSD 3-Clause License
Project-URL: homepage, https://github.com/scqubits/qfit
Project-URL: Repository, https://github.com/scqubits/qfit
Keywords: parameter extraction,superconducting qubits
Classifier: Development Status :: 4 - Beta
Classifier: Intended Audience :: Science/Research
Classifier: License :: OSI Approved :: BSD License
Classifier: Programming Language :: Python
Classifier: Programming Language :: Python :: 3
Classifier: Topic :: Scientific/Engineering
Classifier: Operating System :: MacOS
Classifier: Operating System :: POSIX
Classifier: Operating System :: Unix
Classifier: Operating System :: Microsoft :: Windows
Requires-Python: >=3.10
License-File: LICENSE
Requires-Dist: numpy>=1.14.2
Requires-Dist: scipy>=1.1.0
Requires-Dist: matplotlib>=3.1.2
Requires-Dist: pyside6
Requires-Dist: h5py>=2.7.1
Requires-Dist: scikit-image
Requires-Dist: scqubits>=3.0.0
Requires-Dist: matplotlib-label-lines
Requires-Dist: ipykernel
Requires-Dist: jupyter
Requires-Dist: pathos
Requires-Dist: dill
Requires-Dist: pywavelets
Dynamic: license-file
